pgvector_perf/__init__.py
pgvector_perf/client.py
pgvector_perf/config.py
pgvector_perf/exceptions.py
pgvector_perf/resources/__init__.py
pgvector_perf/resources/databases.py
pgvector_perf/resources/index.py
pgvector_perf/resources/points.py
pgvector_perf/resources/tables.py
pgvector_perf/schemas.py
pgvector_perf/utils.py
pgvector_perf/version.py
pgvector_perf-0.1.0.dist-info/LICENSE
pgvector_perf-0.1.0.dist-info/METADATA
pgvector_perf-0.1.0.dist-info/WHEEL
pgvector_perf-0.1.0.dist-info/RECORD
